uv_func/__init__.py
uv_func/core.py
uv_func/execution.py
uv_func/logging.py
uv_func/py.typed
uv_func-0.1.1.dist-info/WHEEL
uv_func-0.1.1.dist-info/METADATA
uv_func-0.1.1.dist-info/RECORD
