Metadata-Version: 2.3
Name: uv-func
Version: 0.1.1
Summary: A package to run functions within dedicated UV Python environments.
Author: Reda Oulbacha
Author-email: Reda Oulbacha <oulbacha.reda@gmail.com>
Requires-Dist: cloudpickle>=3.1.1
Requires-Dist: portalocker>=3.2.0
Requires-Dist: rich>=14.1.0
Requires-Python: >=3.12
